[
  {
    "id": "2",
    "icon": "Target",
    "reportTitle": "Target vs. Achievement",
    "reportSubTitle": "Comparative sales goals tracking and distribution efficiency.",
    "route": "/targetVsAchievement",
    "status": [
      "On",
      "Target"
    ]
  },
  {
    "id": "3",
    "icon": "UserCheck",
    "reportTitle": "Amolnama",
    "reportSubTitle": "Individual performance history and representative behavioral data.",
    "route": "/amolnama",
    "records": "1,429 entries"
  },
  {
    "id": "4",
    "icon": "StoreOff",
    "reportTitle": "Uncovered Outlet Report",
    "reportSubTitle": "Market gap analysis and missed delivery opportunities in rural sectors.",
    "route": "/uncoveredOutlet",
    "criticality": "High"
  },
  {
    "id": "1",
    "icon": "BriefcaseBusiness",
    "reportTitle": "Half Summary",
    "reportSubTitle": "Mid-period performance metrics and aggregate logistics flow.",
    "route": "/halfSummary",
    "lastUpdated": "2 hours ago"
  }
]